{
  "$schema": "http://json-schema.org/draft-07/schema#",
  "title": "PlanSet",
  "type": "object",
  "properties": {
    "assumptions": {"type": "object"},
    "baseline_cashflow": {"type": "object"},
    "scenarios": {"type": "array", "items": {"type": "object"}},
    "probabilities": {"type": "object"},
    "funding_gaps": {"type": "object"},
    "savings_withdrawals": {"type": "object"},
    "liquidity_runway_months": {"type": "number"},
    "allocation_guidance": {"type": "object"},
    "glidepath": {},
    "rationale": {"type": "string"},
    "data_lineage": {"type": "object"},
    "missing_fields": {"type": "array", "items": {"type": "string"}}
  },
  "required": ["assumptions", "baseline_cashflow", "scenarios", "probabilities", "funding_gaps", "savings_withdrawals", "liquidity_runway_months", "allocation_guidance", "rationale", "data_lineage", "missing_fields"]
}
